deezy/__init__.py
deezy/__main__.py
deezy/audio_encoders/base.py
deezy/audio_encoders/dee/ac4.py
deezy/audio_encoders/dee/atmos.py
deezy/audio_encoders/dee/base.py
deezy/audio_encoders/dee/dd.py
deezy/audio_encoders/dee/ddp.py
deezy/audio_encoders/dee/json/ac4_base.py
deezy/audio_encoders/dee/json/atmos_base.py
deezy/audio_encoders/dee/json/dd_base.py
deezy/audio_encoders/dee/json/dee_json_generator.py
deezy/audio_encoders/delay/__init__.py
deezy/audio_processors/dee.py
deezy/audio_processors/ffmpeg.py
deezy/audio_processors/truehdd.py
deezy/cli/__init__.py
deezy/cli/payload_factory.py
deezy/cli/utils.py
deezy/config/__init__.py
deezy/config/defaults.py
deezy/config/manager.py
deezy/enums/__init__.py
deezy/enums/ac4.py
deezy/enums/atmos.py
deezy/enums/channel_count.py
deezy/enums/codec_format.py
deezy/enums/dd.py
deezy/enums/ddp.py
deezy/enums/ddp_bluray.py
deezy/enums/shared.py
deezy/exceptions/__init__.py
deezy/info/__init__.py
deezy/payloads/ac4.py
deezy/payloads/atmos.py
deezy/payloads/dd.py
deezy/payloads/ddp.py
deezy/payloads/shared.py
deezy/track_info/audio_track_info.py
deezy/track_info/mediainfo.py
deezy/track_info/track_index.py
deezy/track_info/utils.py
deezy/utils/__init__.py
deezy/utils/batch_results.py
deezy/utils/dependencies.py
deezy/utils/exit.py
deezy/utils/file_parser.py
deezy/utils/logger.py
deezy/utils/progress.py
deezy/utils/utils.py
deezy-1.3.14.dist-info/licenses/LICENSE
deezy-1.3.14.dist-info/METADATA
deezy-1.3.14.dist-info/WHEEL
deezy-1.3.14.dist-info/entry_points.txt
deezy-1.3.14.dist-info/top_level.txt
deezy-1.3.14.dist-info/RECORD
