Metadata-Version: 2.4
Name: deezy
Version: 1.3.14
Summary: Dolby Encoding Engine Wrapper
Author: jessielw
License: MIT License
Project-URL: Source, https://github.com/jessielw/deezy
Project-URL: Tracker, https://github.com/jessielw/DeeZy/issues
Keywords: audio,dolby,encoding,dee,ddp,atmos,ac4
Classifier: License :: OSI Approved :: MIT License
Classifier: Programming Language :: Python :: 3
Classifier: Programming Language :: Python :: 3 :: Only
Classifier: Programming Language :: Python :: 3.9
Classifier: Programming Language :: Python :: 3.10
Classifier: Programming Language :: Python :: 3.11
Classifier: Programming Language :: Python :: 3.12
Classifier: Programming Language :: Python :: 3.13
Classifier: Topic :: Multimedia :: Sound/Audio
Classifier: Topic :: Software Development :: Libraries :: Python Modules
Requires-Python: <3.14,>=3.9
License-File: LICENSE
Requires-Dist: pymediainfo
Requires-Dist: tomlkit
Requires-Dist: platformdirs>=2.6.0
Requires-Dist: typing-extensions>=4.15.0
Requires-Dist: rich>=14.1.0
Requires-Dist: oslex2>=1.0.0
Requires-Dist: guessit>=3.8.0
Requires-Dist: unidecode>=1.4.0
Provides-Extra: dev
Requires-Dist: ruff; extra == "dev"
Requires-Dist: pytest; extra == "dev"
Requires-Dist: pytest-cov; extra == "dev"
Requires-Dist: pyinstaller>=6.13.0; extra == "dev"
Requires-Dist: pyinstaller-hooks-contrib>=2025.1; extra == "dev"
Provides-Extra: docs
Requires-Dist: mkdocs>=1.6.1; extra == "docs"
Requires-Dist: mkdocs-material>=9.6.11; extra == "docs"
Requires-Dist: pymdown-extensions>=10.16.1; extra == "docs"
Dynamic: license-file
